Metadata-Version: 2.1
Name: agemo
Version: 0.0.3
Summary: Laplace transformed coalescence times
Home-page: https://github.com/LohseLab/agemo
Author: Gertjan Bisschop
Author-email: gertjanbisschop@gmail.com
License: GNU GPLv3+
Project-URL: Github, https://github.com/LohseLab/agemo
Keywords: Laplace transform,structured coalescent,generating function
Platform: UNKNOWN
Classifier: Programming Language :: Python :: 3
Requires-Python: >=3.7
Provides-Extra: tests
